README.txt
setup.py
presslink/__init__.py
presslink/diff_list.py
presslink/diff_peak_remover.py
presslink/drag_link_bc_interference_check.py
presslink/drag_link_excel_writer.py
presslink/drag_link_graph_plot.py
presslink/drag_link_modular.py
presslink/drag_link_rocker_force.py
presslink/drag_link_sizer.py
presslink/drag_link_user_calculation.py
presslink/kj_conrod_force.py
presslink/kj_excel_writer.py
presslink/kj_modular.py
presslink/kj_rkr_th_finder.py
presslink/kj_sizer.py
presslink/kj_user_calculation.py
presslink/ld_excel_writer.py
presslink/ld_graph_plot.py
presslink/ld_modular.py
presslink/ld_rocker_force.py
presslink/ld_sizer.py
presslink/ld_user_calculation.py
presslink/link4_rj4.py
presslink/link5_rj4_sj1.py
presslink/ml_excel_writer.py
presslink/ml_graph_plot.py
presslink/ml_modular.py
presslink/ml_sizer.py
presslink/ml_ternary_link_force.py
presslink/ml_user_calculation.py
presslink/pretty_graph_datagen.py
presslink/remove_trailing_zeros.py
presslink/shaft.py
presslink/vector_difference.py
presslink.egg-info/PKG-INFO
presslink.egg-info/SOURCES.txt
presslink.egg-info/dependency_links.txt
presslink.egg-info/requires.txt
presslink.egg-info/top_level.txt